trident_api/__init__.py
trident_api/cli.py
trident_api/client.py
trident_api-0.1.0.dist-info/METADATA
trident_api-0.1.0.dist-info/WHEEL
trident_api-0.1.0.dist-info/entry_points.txt
trident_api-0.1.0.dist-info/licenses/LICENSE
trident_api-0.1.0.dist-info/RECORD
